wui/AskBtnLabel.py
wui/Button.py
wui/Color.py
wui/Dialog.py
wui/EventBase.py
wui/Group.py
wui/IOButton.py
wui/IOCom.py
wui/Image.py
wui/InputArea.py
wui/InputBox.py
wui/Label.py
wui/Menu.py
wui/Panel.py
wui/RadioButton.py
wui/SimpleList.py
wui/StyleBase.py
wui/__init__.py
wui/aaa.py
wui/wui.py
wui-1.2.4.dist-info/LICENSE.txt
wui-1.2.4.dist-info/METADATA
wui-1.2.4.dist-info/WHEEL
wui-1.2.4.dist-info/top_level.txt
wui-1.2.4.dist-info/RECORD
